odoo/addons/product_attribute_archive/README.rst
odoo/addons/product_attribute_archive/__init__.py
odoo/addons/product_attribute_archive/__manifest__.py
odoo/addons/product_attribute_archive/i18n/es.po
odoo/addons/product_attribute_archive/i18n/it.po
odoo/addons/product_attribute_archive/i18n/product_attribute_archive.pot
odoo/addons/product_attribute_archive/models/__init__.py
odoo/addons/product_attribute_archive/models/product_attribute.py
odoo/addons/product_attribute_archive/models/product_attribute_value.py
odoo/addons/product_attribute_archive/readme/CONTRIBUTORS.md
odoo/addons/product_attribute_archive/readme/DESCRIPTION.md
odoo/addons/product_attribute_archive/readme/USAGE.md
odoo/addons/product_attribute_archive/static/description/icon.png
odoo/addons/product_attribute_archive/static/description/index.html
odoo/addons/product_attribute_archive/views/product_attribute.xml
odoo_addon_product_attribute_archive-18.0.1.0.0.2.dist-info/METADATA
odoo_addon_product_attribute_archive-18.0.1.0.0.2.dist-info/WHEEL
odoo_addon_product_attribute_archive-18.0.1.0.0.2.dist-info/top_level.txt
odoo_addon_product_attribute_archive-18.0.1.0.0.2.dist-info/RECORD
